lox/__init__.py
lox/__main__.py
lox/lox.py
lox/utils.py
lox/version.py
zf_lox-3.1.0.dist-info/LICENSE
zf_lox-3.1.0.dist-info/METADATA
zf_lox-3.1.0.dist-info/WHEEL
zf_lox-3.1.0.dist-info/entry_points.txt
zf_lox-3.1.0.dist-info/top_level.txt
zf_lox-3.1.0.dist-info/RECORD
