Metadata-Version: 2.1
Name: zf-lox
Version: 3.1.0
Summary: Lox extracts data from LinkedIn posts and saves it to Notion
Author: Zeff Muks
Author-email: zeffmuks@gmail.com
License: MIT
License-File: LICENSE
Requires-Dist: linkedin-api>=2.3.1
Requires-Dist: loguru>=0.7.2
Requires-Dist: pydantic>=2.7.4
Requires-Dist: requests>=2.32.3
Requires-Dist: tqdm>=4.66.5
Requires-Dist: zf-perse>=1.3.0
